server/__init__.py
server/server.py
dpy_http_server-0.1.0.dist-info/METADATA
dpy_http_server-0.1.0.dist-info/WHEEL
dpy_http_server-0.1.0.dist-info/top_level.txt
dpy_http_server-0.1.0.dist-info/RECORD
