Metadata-Version: 2.1
Name: dpy-http-server
Version: 0.1.0
Summary: Efficiently and intuitively create and manage an HTTP web server running in tandem with a discord.py bot
Home-page: https://gitlab.com/marwynnsomridhivej/dpy-http-server
Author: Marwynn Somridhivej
License: MIT
Platform: UNKNOWN
Classifier: License :: OSI Approved :: MIT License
Classifier: Development Status :: 4 - Beta
Classifier: Intended Audience :: Developers
Classifier: Natural Language :: English
Classifier: Programming Language :: Python :: 3.6
Classifier: Programming Language :: Python :: 3.7
Classifier: Programming Language :: Python :: 3.8
Classifier: Programming Language :: Python :: 3.9
Requires-Dist: discord.py
Requires-Dist: aiohttp
